chia_xch/__init__.py
chia_xch/encoding.py
chia_xch/full_node.py
chia_xch/providers.py
chia_xch/rpc_abi.py
chia_xch/types_check.py
chia_xch/types_xch.py
chia_xch/wallet.py
chia_xch/xch.py
chia_xch-1.0.1.dist-info/LICENSE
chia_xch-1.0.1.dist-info/METADATA
chia_xch-1.0.1.dist-info/WHEEL
chia_xch-1.0.1.dist-info/top_level.txt
chia_xch-1.0.1.dist-info/RECORD
