Metadata-Version: 2.1
Name: chia-xch
Version: 1.0.1
Summary: A package interact with bitcoin node
Home-page: https://github.com/wenqinchao/chia-xch
Author: Wen
Author-email: wenqinchao@gmail.com
License: MIT
Platform: UNKNOWN
Classifier: Programming Language :: Python :: 3
Classifier: License :: OSI Approved :: MIT License
Classifier: Operating System :: OS Independent
Requires-Python: >=3.6
License-File: LICENSE
